MANIFEST.in
README.txt
setup.cfg
setup.py
docs/HISTORY.txt
docs/INSTALL.txt
docs/LICENSE.GPL
docs/LICENSE.txt
ploomcake/__init__.py
ploomcake/__init__.pyc
ploomcake.installer.egg-info/PKG-INFO
ploomcake.installer.egg-info/SOURCES.txt
ploomcake.installer.egg-info/dependency_links.txt
ploomcake.installer.egg-info/entry_points.txt
ploomcake.installer.egg-info/namespace_packages.txt
ploomcake.installer.egg-info/not-zip-safe
ploomcake.installer.egg-info/requires.txt
ploomcake.installer.egg-info/top_level.txt
ploomcake/installer/__init__.py
ploomcake/installer/admin.py
ploomcake/installer/configure.zcml
ploomcake/installer/front_page.py
ploomcake/installer/i18n.sh
ploomcake/installer/overrides.zcml
ploomcake/installer/plone-overview.pt
ploomcake/installer/ploomcake-addsite.pt
ploomcake/installer/ploomcake-logo.png
ploomcake/installer/robots.pt
ploomcake/installer/setuphandlers.py
ploomcake/installer/tests.py
ploomcake/installer/demo/demo-website.zexp
ploomcake/installer/locales/ploomcake.installer
ploomcake/installer/locales/ploomcake.installer.pot
ploomcake/installer/locales/en/LC_MESSAGES/ploomcake.installer.po
ploomcake/installer/locales/it/LC_MESSAGES/ploomcake.installer.po
ploomcake/installer/profiles/content/metadata.xml
ploomcake/installer/profiles/content/ploomcake-content.txt