Metadata-Version: 1.0
Name: ploomcake.installer
Version: 0.11
Summary: Ploomcake instance installer
Home-page: https://github.com/ploomcake/ploomcake.installer
Author: Maurizio Lupo
Author-email: maurizio.lupo@redomino.com
License: GPL
Platform: UNKNOWN
Classifier: Framework :: Plone
Classifier: Programming Language :: Python
